fauxpy/__init__.py
fauxpy/constants.py
fauxpy/main.py
fauxpy/version.py
fauxpy/command_line/__init__.py
fauxpy/command_line/analysis_mode/__init__.py
fauxpy/command_line/analysis_mode/handler.py
fauxpy/command_line/pytest_mode/__init__.py
fauxpy/command_line/pytest_mode/fl_option_manager.py
fauxpy/command_line/pytest_mode/handler.py
fauxpy/command_line/pytest_mode/legacy_input.py
fauxpy/command_line/pytest_mode/pytest_option_manager.py
fauxpy/fault_localization/__init__.py
fauxpy/fault_localization/collect_mbfl/__init__.py
fauxpy/fault_localization/collect_mbfl/api_file.py
fauxpy/fault_localization/collect_mbfl/api_lib.py
fauxpy/fault_localization/collect_mbfl/db_manager.py
fauxpy/fault_localization/collect_mbfl/reporter_lib.py
fauxpy/fault_localization/collect_mbfl/session_file.py
fauxpy/fault_localization/collect_mbfl/session_lib.py
fauxpy/fault_localization/collect_ps_info/__init__.py
fauxpy/fault_localization/collect_ps_info/api_file.py
fauxpy/fault_localization/collect_ps_info/api_lib.py
fauxpy/fault_localization/collect_ps_info/db_manager.py
fauxpy/fault_localization/collect_ps_info/reporter_lib.py
fauxpy/fault_localization/collect_ps_info/session_file.py
fauxpy/fault_localization/collect_ps_info/session_lib.py
fauxpy/fault_localization/collect_ps_run/__init__.py
fauxpy/fault_localization/collect_ps_run/api_file.py
fauxpy/fault_localization/collect_ps_run/api_lib.py
fauxpy/fault_localization/collect_ps_run/db_manager.py
fauxpy/fault_localization/collect_ps_run/reporter_lib.py
fauxpy/fault_localization/collect_ps_run/result_type.py
fauxpy/fault_localization/collect_ps_run/session_file.py
fauxpy/fault_localization/collect_ps_run/session_lib.py
fauxpy/fault_localization/granularity/__init__.py
fauxpy/fault_localization/granularity/ast_lib.py
fauxpy/fault_localization/granularity/db_manager.py
fauxpy/fault_localization/granularity/function_level.py
fauxpy/fault_localization/mbfl/__init__.py
fauxpy/fault_localization/mbfl/db_manager.py
fauxpy-0.7.0.dist-info/LICENSE
fauxpy-0.7.0.dist-info/METADATA
fauxpy-0.7.0.dist-info/WHEEL
fauxpy-0.7.0.dist-info/entry_points.txt
fauxpy-0.7.0.dist-info/top_level.txt
fauxpy-0.7.0.dist-info/RECORD
