Metadata-Version: 2.1
Name: fauxpy
Version: 0.7.0
Summary: An automated fault localization tool for Python programs.
Home-page: https://fauxpy.readthedocs.io
Author: Mohammad Rezaalipour
Author-email: rezaalipour.mohammad@gmail.com
Requires-Python: >=3.7
License-File: LICENSE
Requires-Dist: pytest>=3.1.2
Requires-Dist: coverage>=6.2
Requires-Dist: cosmic-ray==8.3.5
Requires-Dist: astor~=0.8.1
Requires-Dist: pytest-timeout==2.1.0
Requires-Dist: wheel
Requires-Dist: pyllmut
